{
  "run_id": "20260619T084949Z_practice-fills",
  "action": "practice-fills",
  "status": "ERROR",
  "return_code": 1,
  "command": [
    "D:\\AI\\apps\\exe\\anaconda3\\pythonw.exe",
    "-m",
    "quant.apps.start",
    "practice-fills"
  ],
  "started_at": "2026-06-19T08:49:49.911933+00:00",
  "ended_at": "2026-06-19T08:49:50.006230+00:00",
  "stdout": "[RUN] Practice fill import\n  D:\\AI\\apps\\exe\\anaconda3\\pythonw.exe -m quant.apps.fill import --source research_store/sample/broker_fills_sample.csv --output-template research_store/sample/broker_fills_sample.imported.csv --report research_store/reports/manual_fill_import_sample.json --report-md research_store/reports/manual_fill_import_sample.md --audit-log research_store/reports/manual_fill_import_sample_audit.jsonl --validate-only\n  [FAIL] Step 'Practice fill import' failed with exit code 1\n",
  "stderr": "Traceback (most recent call last):\n  File \"<frozen runpy>\", line 198, in _run_module_as_main\n  File \"<frozen runpy>\", line 88, in _run_code\n  File \"D:\\Agent\\codex\\workspace\\stock-quant\\quant\\apps\\start.py\", line 889, in <module>\n    main()\n    ~~~~^^\n  File \"D:\\Agent\\codex\\workspace\\stock-quant\\quant\\apps\\start.py\", line 203, in main\n    run_steps(steps, dry_run=bool(args.dry_run), keep_going=bool(args.keep_going))\n    ~~~~~~~~~^^^^^^^^^^^^^^^^^^^^^^^^^^^^^^^^^^^^^^^^^^^^^^^^^^^^^^^^^^^^^^^^^^^^^\n  File \"D:\\Agent\\codex\\workspace\\stock-quant\\quant\\apps\\start.py\", line 568, in run_steps\n    raise RuntimeError(msg)\nRuntimeError: Step 'Practice fill import' failed with exit code 1\n",
  "log_path": "research_store\\web_runs\\20260619T084949Z_practice-fills.log",
  "json_path": "research_store\\web_runs\\20260619T084949Z_practice-fills.json"
}